sqlalchemy_ceodbc/__init__.py
sqlalchemy_ceodbc/connector.py
sqlalchemy_ceodbc/dialect.py
sqlalchemy_ceodbc-0.1.0.dist-info/DESCRIPTION.rst
sqlalchemy_ceodbc-0.1.0.dist-info/METADATA
sqlalchemy_ceodbc-0.1.0.dist-info/RECORD
sqlalchemy_ceodbc-0.1.0.dist-info/WHEEL
sqlalchemy_ceodbc-0.1.0.dist-info/entry_points.txt
sqlalchemy_ceodbc-0.1.0.dist-info/metadata.json
sqlalchemy_ceodbc-0.1.0.dist-info/top_level.txt
